MANIFEST.in
README.txt
bootstrap.py
setup.cfg
setup.py
bg/__init__.py
bg.solr.egg-info/PKG-INFO
bg.solr.egg-info/SOURCES.txt
bg.solr.egg-info/dependency_links.txt
bg.solr.egg-info/entry_points.txt
bg.solr.egg-info/namespace_packages.txt
bg.solr.egg-info/not-zip-safe
bg.solr.egg-info/paster_plugins.txt
bg.solr.egg-info/requires.txt
bg.solr.egg-info/top_level.txt
bg/solr/__init__.py
bg/solr/configure.zcml
bg/solr/header.txt
bg/solr/patches.py
bg/solr/profiles.zcml
bg/solr/setuphandlers.py
bg/solr/skins.zcml
bg/solr/tests.py
bg/solr/version.txt
bg/solr/browser/__init__.py
bg/solr/browser/configure.zcml
bg/solr/browser/solr.py
bg/solr/browser/solr_search.pt
bg/solr/browser/images/README.txt
bg/solr/browser/stylesheets/README.txt
bg/solr/browser/stylesheets/main.css
bg/solr/locales/README.txt
bg/solr/profiles/default/bg.solr_various.txt
bg/solr/profiles/default/cssregistry.xml
bg/solr/profiles/default/jsregistry.xml
bg/solr/profiles/default/metadata.xml
bg/solr/profiles/default/propertiestool.xml
bg/solr/profiles/default/skins.xml
bg/solr/profiles/default/viewlets.xml
bg/solr/skins/bg_solr/CONTENT.txt
docs/HISTORY.txt
docs/INSTALL.txt
docs/LICENSE.GPL
docs/LICENSE.txt
docs/Makefile
docs/make.bat
docs/source/conf.py
docs/source/index.rst