Metadata-Version: 1.0
Name: bg.solr
Version: 0.2
Summary: bg.solr
Home-page: http://svn.plone.org/svn/collective/
Author: Andreas Jung
Author-email: info@zopyx.com
License: GPL
Platform: UNKNOWN
Classifier: Framework :: Plone
Classifier: Programming Language :: Python
